[
  {
    "ContainingType": "WebAPI_Practica01.Controllers.ArticuloController",
    "Method": "Get",
    "RelativePath": "api/Articulo",
    "HttpMethod": "GET",
    "IsController": true,
    "Order": 0,
    "Parameters": [],
    "ReturnTypes": []
  },
  {
    "ContainingType": "WebAPI_Practica01.Controllers.ArticuloController",
    "Method": "Post",
    "RelativePath": "api/Articulo",
    "HttpMethod": "POST",
    "IsController": true,
    "Order": 0,
    "Parameters": [
      {
        "Name": "articulo",
        "Type": "LOCURA.Dominio.Articulo",
        "IsRequired": true
      }
    ],
    "ReturnTypes": []
  },
  {
    "ContainingType": "WebAPI_Practica01.Controllers.ArticuloController",
    "Method": "Get",
    "RelativePath": "api/Articulo/{id}",
    "HttpMethod": "GET",
    "IsController": true,
    "Order": 0,
    "Parameters": [
      {
        "Name": "id",
        "Type": "System.Int32",
        "IsRequired": true
      }
    ],
    "ReturnTypes": []
  },
  {
    "ContainingType": "WebAPI_Practica01.Controllers.ArticuloController",
    "Method": "Put",
    "RelativePath": "api/Articulo/{id}",
    "HttpMethod": "PUT",
    "IsController": true,
    "Order": 0,
    "Parameters": [
      {
        "Name": "id",
        "Type": "System.Int32",
        "IsRequired": true
      },
      {
        "Name": "articulo",
        "Type": "LOCURA.Dominio.Articulo",
        "IsRequired": true
      }
    ],
    "ReturnTypes": []
  },
  {
    "ContainingType": "WebAPI_Practica01.Controllers.ArticuloController",
    "Method": "Delete",
    "RelativePath": "api/Articulo/{id}",
    "HttpMethod": "DELETE",
    "IsController": true,
    "Order": 0,
    "Parameters": [
      {
        "Name": "id",
        "Type": "System.Int32",
        "IsRequired": true
      }
    ],
    "ReturnTypes": []
  },
  {
    "ContainingType": "WebAPI_Practica01.Controllers.FacturaController",
    "Method": "Get",
    "RelativePath": "api/Factura",
    "HttpMethod": "GET",
    "IsController": true,
    "Order": 0,
    "Parameters": [],
    "ReturnTypes": []
  },
  {
    "ContainingType": "WebAPI_Practica01.Controllers.FacturaController",
    "Method": "Post",
    "RelativePath": "api/Factura",
    "HttpMethod": "POST",
    "IsController": true,
    "Order": 0,
    "Parameters": [
      {
        "Name": "factura",
        "Type": "LOCURA.Dominio.Factura",
        "IsRequired": true
      }
    ],
    "ReturnTypes": []
  },
  {
    "ContainingType": "WebAPI_Practica01.Controllers.FacturaController",
    "Method": "Get",
    "RelativePath": "api/Factura/{id}",
    "HttpMethod": "GET",
    "IsController": true,
    "Order": 0,
    "Parameters": [
      {
        "Name": "id",
        "Type": "System.Int32",
        "IsRequired": true
      }
    ],
    "ReturnTypes": []
  },
  {
    "ContainingType": "WebAPI_Practica01.Controllers.FacturaController",
    "Method": "Put",
    "RelativePath": "api/Factura/{id}",
    "HttpMethod": "PUT",
    "IsController": true,
    "Order": 0,
    "Parameters": [
      {
        "Name": "id",
        "Type": "System.Int32",
        "IsRequired": true
      },
      {
        "Name": "factura",
        "Type": "LOCURA.Dominio.Factura",
        "IsRequired": true
      }
    ],
    "ReturnTypes": []
  },
  {
    "ContainingType": "WebAPI_Practica01.Controllers.FacturaController",
    "Method": "Delete",
    "RelativePath": "api/Factura/{id}",
    "HttpMethod": "DELETE",
    "IsController": true,
    "Order": 0,
    "Parameters": [
      {
        "Name": "id",
        "Type": "System.Int32",
        "IsRequired": true
      }
    ],
    "ReturnTypes": []
  },
  {
    "ContainingType": "WebAPI_Practica01.Controllers.PagoController",
    "Method": "Get",
    "RelativePath": "api/Pago",
    "HttpMethod": "GET",
    "IsController": true,
    "Order": 0,
    "Parameters": [],
    "ReturnTypes": []
  },
  {
    "ContainingType": "WebAPI_Practica01.Controllers.PagoController",
    "Method": "Post",
    "RelativePath": "api/Pago",
    "HttpMethod": "POST",
    "IsController": true,
    "Order": 0,
    "Parameters": [
      {
        "Name": "fp",
        "Type": "LOCURA.Dominio.FormaPago",
        "IsRequired": true
      }
    ],
    "ReturnTypes": []
  },
  {
    "ContainingType": "WebAPI_Practica01.Controllers.PagoController",
    "Method": "Get",
    "RelativePath": "api/Pago/{id}",
    "HttpMethod": "GET",
    "IsController": true,
    "Order": 0,
    "Parameters": [
      {
        "Name": "id",
        "Type": "System.Int32",
        "IsRequired": true
      }
    ],
    "ReturnTypes": []
  },
  {
    "ContainingType": "WebAPI_Practica01.Controllers.PagoController",
    "Method": "Put",
    "RelativePath": "api/Pago/{id}",
    "HttpMethod": "PUT",
    "IsController": true,
    "Order": 0,
    "Parameters": [
      {
        "Name": "id",
        "Type": "System.Int32",
        "IsRequired": true
      },
      {
        "Name": "fp",
        "Type": "LOCURA.Dominio.FormaPago",
        "IsRequired": true
      }
    ],
    "ReturnTypes": []
  },
  {
    "ContainingType": "WebAPI_Practica01.Controllers.PagoController",
    "Method": "Delete",
    "RelativePath": "api/Pago/{id}",
    "HttpMethod": "DELETE",
    "IsController": true,
    "Order": 0,
    "Parameters": [
      {
        "Name": "id",
        "Type": "System.Int32",
        "IsRequired": true
      }
    ],
    "ReturnTypes": []
  }
]